dicarlo_lab_to_nwb/__init__.py
dicarlo_lab_to_nwb/conversion/__init__.py
dicarlo_lab_to_nwb/conversion/behaviorinterface.py
dicarlo_lab_to_nwb/conversion/conversion_notes.md
dicarlo_lab_to_nwb/conversion/convert_session.py
dicarlo_lab_to_nwb/conversion/data_locator.py
dicarlo_lab_to_nwb/conversion/metadata.yaml
dicarlo_lab_to_nwb/conversion/nwbconverter.py
dicarlo_lab_to_nwb/conversion/pipeline.py
dicarlo_lab_to_nwb/conversion/probe.py
dicarlo_lab_to_nwb/conversion/probe_info.csv
dicarlo_lab_to_nwb/conversion/psth.py
dicarlo_lab_to_nwb/conversion/showcase_notebook.ipynb
dicarlo_lab_to_nwb/conversion/stimuli_interface.py
dicarlo_lab_to_nwb/conversion/assets/connectivity.png
dicarlo_lab_to_nwb/conversion/assets/electrode_width_utah_array.png
dicarlo_lab_to_nwb/conversion/assets/intan_recording_system.jpg
dicarlo_lab_to_nwb/conversion/assets/utah_array.png
dicarlo_lab_to_nwb/conversion/assets/utah_array_pedestal_connector.png
dicarlo_lab_to_nwb-0.1.3.dist-info/METADATA
dicarlo_lab_to_nwb-0.1.3.dist-info/WHEEL
dicarlo_lab_to_nwb-0.1.3.dist-info/licenses/LICENSE
dicarlo_lab_to_nwb-0.1.3.dist-info/RECORD
