Metadata-Version: 2.3
Name: dicarlo-lab-to-nwb
Version: 0.1.3
Summary: NWB conversion scripts, functions, and classes for DiCarlo conversion
Project-URL: Repository, https://github.com/catalystneuro/dicarlo-lab-to-nwb
Author-email: Heberto Mayorquin <h.mayorquin@gmail.com>
License: MIT License
License-File: LICENSE
Classifier: Programming Language :: Python :: 3.9
Classifier: Programming Language :: Python :: 3.10
Classifier: Programming Language :: Python :: 3.11
Classifier: Programming Language :: Python :: 3.12
Requires-Python: >=3.9
Requires-Dist: docker
Requires-Dist: matplotlib
Requires-Dist: ndx-binned-spikes==0.2.0
Requires-Dist: neo==0.13.2
Requires-Dist: neuroconv[video]==0.6.4
Requires-Dist: numba
Requires-Dist: pillow>=10.3.0
Requires-Dist: probeinterface==0.2.23
Requires-Dist: psutil
Requires-Dist: spikeinterface==0.101.1
